ipsetcalc/__init__.py
ipsetcalc/main.py
ipsetcalc-0.1.0.dist-info/METADATA
ipsetcalc-0.1.0.dist-info/WHEEL
ipsetcalc-0.1.0.dist-info/entry_points.txt
ipsetcalc-0.1.0.dist-info/RECORD
